x2c.py
src/__init__.py
src/cli_utils.py
src/x2c_converters.py
xmi2conll-0.1.6.dist-info/LICENSE
xmi2conll-0.1.6.dist-info/METADATA
xmi2conll-0.1.6.dist-info/WHEEL
xmi2conll-0.1.6.dist-info/entry_points.txt
xmi2conll-0.1.6.dist-info/top_level.txt
xmi2conll-0.1.6.dist-info/RECORD
