Metadata-Version: 2.1
Name: xmi2conll
Version: 0.1.6
Summary: Simple CLI to convert any annotated document in UIMA CAS XMI to CONLL format (IOB schema support).
Home-page: https://github.com/Lucaterre/xmi2conll
Author: Lucas Terriel
License: MIT
Classifier: License :: OSI Approved :: MIT License
Classifier: Intended Audience :: Developers
Classifier: Intended Audience :: Education
Classifier: Intended Audience :: Science/Research
Classifier: Programming Language :: Python :: 3.7
Classifier: Programming Language :: Python :: 3.8
Classifier: Operating System :: OS Independent
Requires-Python: >=3.7
License-File: LICENSE
Requires-Dist: click (==8.1.3)
Requires-Dist: pyfiglet (==0.8.post1)
Requires-Dist: dkpro-cassis (==0.7.2)
Requires-Dist: tqdm (==4.64.1)
Requires-Dist: termcolor (==2.0.1)
Requires-Dist: pandas (==1.5.0)
Requires-Dist: numpy (==1.23.3)
